acex/__init__.py
acex/ai_ops/__init__.py
acex/ai_ops/ai_ops.py
acex/ai_ops/settings.py
acex/api/__init__.py
acex/api/api.py
acex/api/routers/ai_ops.py
acex/api/routers/assetclusters.py
acex/api/routers/assets.py
acex/api/routers/device_configs.py
acex/api/routers/logical_nodes.py
acex/api/routers/management_connections.py
acex/api/routers/neds.py
acex/api/routers/node_instances.py
acex/automation_engine/__init__.py
acex/automation_engine/automationengine.py
acex/automation_engine/integrations.py
acex/compilers/__init__.py
acex/compilers/compiled_logical_node.py
acex/compilers/config_compiler.py
acex/config_map/__init__.py
acex/config_map/config_map.py
acex/config_map/context.py
acex/config_map/filter.py
acex/configuration/__init__.py
acex/configuration/components/__init__.py
acex/configuration/components/base_component.py
acex/configuration/components/interfaces/__init__.py
acex/configuration/components/interfaces/interfaces.py
acex/configuration/components/lacp/__init__.py
acex/configuration/components/lacp/lacp.py
acex/configuration/components/network_instances/__init__.py
acex/configuration/components/network_instances/network_instances.py
acex/configuration/components/system/__init__.py
acex/configuration/components/system/logging.py
acex/configuration/components/system/ntp.py
acex/configuration/components/system/ssh.py
acex/configuration/components/system/system.py
acex/configuration/components/vlan/__init__.py
acex/configuration/components/vlan/vlan.py
acex/configuration/configuration.py
acex/constants.py
acex/database/__init__.py
acex/database/connection.py
acex/database/db_manager.py
acex/device_configs/__init__.py
acex/device_configs/device_config_manager.py
acex/exceptions/__init__.py
acex/exceptions/standard.py
acex/inventory/__init__.py
acex/inventory/asset_cluster_manager.py
acex/inventory/inventory.py
acex/inventory/logical_node_service.py
acex/inventory/node_service.py
acex/management_connections/__init__.py
acex-3.5.0.dist-info/METADATA
acex-3.5.0.dist-info/WHEEL
acex-3.5.0.dist-info/RECORD
